chico_dico/__init__.py
chico_dico/__main__.py
chico_dico/chico.py
chico_dico/dico.py
chico_dico/game.py
chico_dico/gradio_ui.py
chico_dico/magic.py
chico_dico/magic_max.py
chico_dico/poker.py
chico_dico/images/chico.png
chico_dico/images/dico.png
chico_dico/images/profile.jpg
chico_dico-1.0.1.dist-info/METADATA
chico_dico-1.0.1.dist-info/WHEEL
chico_dico-1.0.1.dist-info/entry_points.txt
chico_dico-1.0.1.dist-info/licenses/LICENSE
chico_dico-1.0.1.dist-info/RECORD
