Metadata-Version: 2.4
Name: chico_dico
Version: 1.0.1
Summary: chico dico magic
Project-URL: repository, https://github.com/luochang212/chico-dico-magic
Project-URL: bug-tracker, https://github.com/luochang212/chico-dico-magic/issues
Project-URL: documentation, https://luochang212.github.io/posts/chico_dico_magic
Author: luochang
Author-email: luochang212@gmail.com
License: Apache-2.0
License-File: LICENSE
Keywords: magic,poker
Classifier: License :: OSI Approved :: Apache Software License
Classifier: Operating System :: MacOS
Classifier: Operating System :: Microsoft :: Windows
Classifier: Operating System :: Unix
Classifier: Programming Language :: Python
Classifier: Programming Language :: Python :: 3 :: Only
Classifier: Programming Language :: Python :: 3.8
Classifier: Programming Language :: Python :: 3.9
Classifier: Programming Language :: Python :: 3.10
Classifier: Programming Language :: Python :: 3.11
Classifier: Programming Language :: Python :: 3.12
Classifier: Topic :: Scientific/Engineering :: Mathematics
Requires-Python: >=3.8
Requires-Dist: click
Requires-Dist: gradio
